compscat/__init__.py
compscat/__main__.py
compscat/constants.py
compscat/cross_section.py
compscat/generate_event.py
compscat/plotting.py
compscat/save_events.py
compscat-0.3.0.dist-info/LICENSE
compscat-0.3.0.dist-info/METADATA
compscat-0.3.0.dist-info/WHEEL
compscat-0.3.0.dist-info/top_level.txt
compscat-0.3.0.dist-info/RECORD
