Metadata-Version: 2.1
Name: compscat
Version: 0.3.0
Summary: Monte Carlo Simulation of Compton Scattering
Home-page: https://github.com/amanmdesai/compscat
Author: Aman Desai
Author-email: amanmukeshdesai@gmail.com
Maintainer: Aman Desai
Maintainer-email: amanmukeshdesai@gmail.com
Classifier: License :: OSI Approved :: MIT License
Classifier: Programming Language :: Python :: 3
Classifier: Programming Language :: Python :: 3.8
Classifier: Programming Language :: Python :: 3.9
Classifier: Programming Language :: Python :: 3.10
Classifier: Topic :: Scientific/Engineering :: Physics
Classifier: Operating System :: Unix
Classifier: Operating System :: Microsoft :: Windows
Classifier: Operating System :: MacOS
License-File: LICENSE
Requires-Dist: numpy
Requires-Dist: uproot
Requires-Dist: matplotlib
Requires-Dist: pandas
